RCSParser/__init__.py
RCSParser/config-example.py
RCSParser/example.py
RCSParser/sc_parser.py
rcsparser-0.0.1.dist-info/METADATA
rcsparser-0.0.1.dist-info/WHEEL
rcsparser-0.0.1.dist-info/licenses/LICENSE
rcsparser-0.0.1.dist-info/RECORD
