Metadata-Version: 2.1
Name: RCSParser
Version: 0.0.1
Summary: Rockstar Social Club Parser
Project-URL: Documentation, https://github.com/Makcxim/RCSParser#readme
Project-URL: Issues, https://github.com/Makcxim/RCSParser/issues
Project-URL: Source, https://github.com/Makcxim/RCSParser
Author: Makcxim
License-File: LICENSE
Classifier: Development Status :: 4 - Beta
Classifier: Programming Language :: Python
Classifier: Programming Language :: Python :: 3.10
Classifier: Programming Language :: Python :: 3.11
Classifier: Programming Language :: Python :: Implementation :: CPython
Classifier: Programming Language :: Python :: Implementation :: PyPy
Requires-Python: >=3.10
